easycv/__init__.py
easycv/version.py
easycv/apis/__init__.py
easycv/apis/export.py
easycv/apis/test.py
easycv/apis/train.py
easycv/apis/train_misc.py
easycv/configs/__init__.py
easycv/configs/base.py
easycv/configs/classification/cifar10/r50_b128_300e_jpg.py
easycv/configs/classification/cifar10/swintiny_b64_5e_jpg.py
easycv/configs/classification/imagenet/common/classification_base.py
easycv/configs/classification/imagenet/common/dataset/imagenet_classification.py
easycv/configs/classification/imagenet/deit/deit_base_patch16_224.py
easycv/configs/classification/imagenet/deit/deit_schedule.py
easycv/configs/classification/imagenet/deit/imagenet_deit_base_hydra_layer12_patch16_224_jpg.py
easycv/configs/classification/imagenet/deit/imagenet_deit_base_hydra_layer8_patch16_224_jpg.py
easycv/configs/classification/imagenet/deit/imagenet_deit_base_patch16_224_jpg.py
easycv/configs/classification/imagenet/deit/randaug_imagenet_classification.py
easycv/configs/classification/imagenet/deitiii/deitiii_base_patch16_192.py
easycv/configs/classification/imagenet/deitiii/deitiii_schedule.py
easycv/configs/classification/imagenet/deitiii/imagenet_deitiii_base_patch16_192_jpg.py
easycv/configs/classification/imagenet/deitiii/imagenet_deitiii_large_patch16_192_jpg.py
easycv/configs/classification/imagenet/deitiii/imagenet_deitiii_small_patch16_224_jpg.py
easycv/configs/classification/imagenet/deitiii/threeaug_imagenet_classification_192.py
easycv/configs/classification/imagenet/deitiii/threeaug_imagenet_classification_224.py
easycv/configs/classification/imagenet/edgevit/EdgeVit_b512x8_300e_jpg.py
easycv/configs/classification/imagenet/edgevit/imagenet_edgeVIT_s_jpg.py
easycv/configs/classification/imagenet/edgevit/imagenet_edgeVIT_xs_jpg.py
easycv/configs/classification/imagenet/edgevit/imagenet_edgeVIT_xxs_jpg.py
easycv/configs/classification/imagenet/efficientformer/efficientformer_l1.py
easycv/configs/classification/imagenet/efficientformer/efficientformer_l3.py
pai_easycv-0.11.7.dist-info/METADATA
pai_easycv-0.11.7.dist-info/WHEEL
pai_easycv-0.11.7.dist-info/top_level.txt
pai_easycv-0.11.7.dist-info/RECORD
