Metadata-Version: 2.1
Name: pai-easycv
Version: 0.11.7
Summary: An all-in-one toolkit for computer vision
Home-page: https://github.com/alibaba/EasyCV.git
Author: Alibaba PAI team
Author-email: easycv@list.alibaba-inc.com
License: Apache License 2.0
Keywords: self-supvervised,classification,vision
Classifier: Development Status :: 4 - Beta
Classifier: License :: OSI Approved :: Apache Software License
Classifier: Operating System :: OS Independent
Classifier: Programming Language :: Python :: 3
Classifier: Programming Language :: Python :: 3.5
Classifier: Programming Language :: Python :: 3.6
Classifier: Programming Language :: Python :: 3.7
Requires-Dist: albumentations
Requires-Dist: cityscapesscripts
Requires-Dist: dataclasses
Requires-Dist: decord
Requires-Dist: einops
Requires-Dist: future
Requires-Dist: fvcore
Requires-Dist: h5py
Requires-Dist: imgaug
Requires-Dist: json-tricks
Requires-Dist: jsonplus
Requires-Dist: lmdb
Requires-Dist: numba
Requires-Dist: numpy
Requires-Dist: nuscenes-devkit
Requires-Dist: onnxruntime
Requires-Dist: opencv-python
Requires-Dist: oss2
Requires-Dist: packaging
Requires-Dist: Pillow
Requires-Dist: prettytable
Requires-Dist: pyclipper
Requires-Dist: pycocotools
Requires-Dist: pytorch-metric-learning (>=0.9.89)
Requires-Dist: rapidfuzz
Requires-Dist: scikit-image
Requires-Dist: scikit-learn
Requires-Dist: seaborn
Requires-Dist: shapely (==1.8.4)
Requires-Dist: tensorboard
Requires-Dist: thop
Requires-Dist: timm (==0.5.4)
Requires-Dist: transformers
Requires-Dist: wget
Requires-Dist: xtcocotools
Requires-Dist: yacs
